pygini/__init__.py
pygini/gini.py
pygini-1.0.1.dist-info/LICENSE
pygini-1.0.1.dist-info/METADATA
pygini-1.0.1.dist-info/WHEEL
pygini-1.0.1.dist-info/top_level.txt
pygini-1.0.1.dist-info/RECORD
