Metadata-Version: 2.1
Name: pygini
Version: 1.0.1
Summary: Compute the Gini index.
Home-page: https://github.com/mckib2/pygini
Author: Nicholas McKibben
Author-email: nicholas.bgp@gmail.com
License: GPLv3
Keywords: gini gini-index sparsity
Platform: UNKNOWN
Requires-Python: >=3.6
Requires-Dist: numpy (>=1.17.4)
